{"v":5,"entries":{"event-eventdetailview--docs":{"id":"event-eventdetailview--docs","title":"Event/EventDetailView","name":"Docs","importPath":"./src/app/event/[id]/EventDetailView.stories.tsx","type":"docs","tags":["dev","test","manifest","autodocs"],"storiesImports":[]},"event-eventdetailview--default":{"type":"story","subtype":"story","id":"event-eventdetailview--default","name":"Default","title":"Event/EventDetailView","importPath":"./src/app/event/[id]/EventDetailView.stories.tsx","componentPath":"./src/app/event/[id]/EventDetailView.tsx","tags":["dev","test","manifest","autodocs"],"exportName":"Default"},"skeletons-eventdetailsuspense--docs":{"id":"skeletons-eventdetailsuspense--docs","title":"Skeletons/EventDetailSuspense","name":"Docs","importPath":"./src/app/event/[id]/loading.stories.tsx","type":"docs","tags":["dev","test","manifest","autodocs"],"storiesImports":[]},"skeletons-eventdetailsuspense--default":{"type":"story","subtype":"story","id":"skeletons-eventdetailsuspense--default","name":"Default","title":"Skeletons/EventDetailSuspense","importPath":"./src/app/event/[id]/loading.stories.tsx","componentPath":"./src/app/event/[id]/loading.tsx","tags":["dev","test","manifest","autodocs"],"exportName":"Default"},"event-eventpagination--docs":{"id":"event-eventpagination--docs","title":"Event/EventPagination","name":"Docs","importPath":"./src/components/event/EventPagination.stories.tsx","type":"docs","tags":["dev","test","manifest","autodocs"],"storiesImports":[]},"event-eventpagination--default":{"type":"story","subtype":"story","id":"event-eventpagination--default","name":"Default","title":"Event/EventPagination","importPath":"./src/components/event/EventPagination.stories.tsx","componentPath":"./src/components/event/EventPagination.tsx","tags":["dev","test","manifest","autodocs"],"exportName":"Default"},"event-eventsearchform--docs":{"id":"event-eventsearchform--docs","title":"Event/EventSearchForm","name":"Docs","importPath":"./src/components/event/EventSearchForm.stories.tsx","type":"docs","tags":["dev","test","manifest","autodocs"],"storiesImports":[]},"event-eventsearchform--default":{"type":"story","subtype":"story","id":"event-eventsearchform--default","name":"Default","title":"Event/EventSearchForm","importPath":"./src/components/event/EventSearchForm.stories.tsx","componentPath":"./src/components/event/EventSearchForm.tsx","tags":["dev","test","manifest","autodocs"],"exportName":"Default"},"event-eventtag--docs":{"id":"event-eventtag--docs","title":"Event/EventTag","name":"Docs","importPath":"./src/components/event/EventTag.stories.ts","type":"docs","tags":["dev","test","manifest","autodocs"],"storiesImports":[]},"event-eventtag--comic":{"type":"story","subtype":"story","id":"event-eventtag--comic","name":"Comic","title":"Event/EventTag","importPath":"./src/components/event/EventTag.stories.ts","componentPath":"./src/components/event/EventTag.tsx","tags":["dev","test","manifest","autodocs"],"exportName":"Comic"},"event-eventtag--game":{"type":"story","subtype":"story","id":"event-eventtag--game","name":"Game","title":"Event/EventTag","importPath":"./src/components/event/EventTag.stories.ts","componentPath":"./src/components/event/EventTag.tsx","tags":["dev","test","manifest","autodocs"],"exportName":"Game"},"event-eventcard--docs":{"id":"event-eventcard--docs","title":"Event/EventCard","name":"Docs","importPath":"./src/components/event/eventCard/EventCard.stories.tsx","type":"docs","tags":["dev","test","manifest","autodocs"],"storiesImports":[]},"event-eventcard--default":{"type":"story","subtype":"story","id":"event-eventcard--default","name":"Default","title":"Event/EventCard","importPath":"./src/components/event/eventCard/EventCard.stories.tsx","componentPath":"./src/components/event/eventCard/EventCard.tsx","tags":["dev","test","manifest","autodocs"],"exportName":"Default"},"event-eventfilter--docs":{"id":"event-eventfilter--docs","title":"Event/EventFilter","name":"Docs","importPath":"./src/components/event/eventFilter/EventFilter.stories.tsx","type":"docs","tags":["dev","test","manifest","autodocs"],"storiesImports":[]},"event-eventfilter--default":{"type":"story","subtype":"story","id":"event-eventfilter--default","name":"Default","title":"Event/EventFilter","importPath":"./src/components/event/eventFilter/EventFilter.stories.tsx","componentPath":"./src/components/event/eventFilter/EventFilter.tsx","tags":["dev","test","manifest","autodocs"],"exportName":"Default"},"event-eventlist--docs":{"id":"event-eventlist--docs","title":"Event/EventList","name":"Docs","importPath":"./src/components/event/eventList/EventList.stories.ts","type":"docs","tags":["dev","test","manifest","autodocs"],"storiesImports":[]},"event-eventlist--default":{"type":"story","subtype":"story","id":"event-eventlist--default","name":"Default","title":"Event/EventList","importPath":"./src/components/event/eventList/EventList.stories.ts","componentPath":"./src/components/event/eventList/EventList.tsx","tags":["dev","test","manifest","autodocs"],"exportName":"Default"},"event-eventlistlayouttogglebuttons--docs":{"id":"event-eventlistlayouttogglebuttons--docs","title":"Event/EventListLayoutToggleButtons","name":"Docs","importPath":"./src/components/event/eventList/EventListLayoutToggleButtons.stories.ts","type":"docs","tags":["dev","test","manifest","autodocs"],"storiesImports":[]},"event-eventlistlayouttogglebuttons--default":{"type":"story","subtype":"story","id":"event-eventlistlayouttogglebuttons--default","name":"Default","title":"Event/EventListLayoutToggleButtons","importPath":"./src/components/event/eventList/EventListLayoutToggleButtons.stories.ts","componentPath":"./src/components/event/eventList/EventListLayoutToggleButtons.tsx","tags":["dev","test","manifest","autodocs"],"exportName":"Default"}}}